tucker_trucker/__init__.py
tucker_trucker/__main__.py
tucker_trucker/constants.py
tucker_trucker/entities.py
tucker_trucker/game_engine.py
tucker_trucker/main.py
tucker_trucker/ui.py
tucker_trucker/assets/tucker_placeholder.png
tucker_trucker-1.1.0.dist-info/licenses/LICENSE
tucker_trucker-1.1.0.dist-info/METADATA
tucker_trucker-1.1.0.dist-info/WHEEL
tucker_trucker-1.1.0.dist-info/entry_points.txt
tucker_trucker-1.1.0.dist-info/top_level.txt
tucker_trucker-1.1.0.dist-info/RECORD
