Metadata-Version: 2.4
Name: tucker-trucker
Version: 1.1.0
Summary: A 2D market timing and strategy game featuring Tucker the Boston Terrier delivering goods around town!
Author-email: Jeremy Evans <JeremyEvans@hey.com>
License: MIT License
Project-URL: Homepage, https://github.com/jeremevans/tucker-trucker
Project-URL: Bug Reports, https://github.com/jeremevans/tucker-trucker/issues
Project-URL: Source, https://github.com/jeremevans/tucker-trucker
Keywords: game,pygame,strategy,trading,boston-terrier,2d-game
Classifier: Development Status :: 5 - Production/Stable
Classifier: Intended Audience :: End Users/Desktop
Classifier: License :: OSI Approved :: MIT License
Classifier: Operating System :: OS Independent
Classifier: Programming Language :: Python :: 3
Classifier: Programming Language :: Python :: 3.7
Classifier: Programming Language :: Python :: 3.8
Classifier: Programming Language :: Python :: 3.9
Classifier: Programming Language :: Python :: 3.10
Classifier: Programming Language :: Python :: 3.11
Classifier: Programming Language :: Python :: 3.12
Classifier: Topic :: Games/Entertainment
Classifier: Topic :: Games/Entertainment :: Simulation
Requires-Python: >=3.7
License-File: LICENSE
Requires-Dist: pygame>=2.5.0
Requires-Dist: numpy>=1.24.0
Dynamic: license-file
